tablet_tilt_joystick/__init__.py
tablet_tilt_joystick/__main__.py
tablet_tilt_joystick/joystick_control.py
tablet_tilt_joystick/server.py
tablet_tilt_joystick/show_qr_link.py
tablet_tilt_joystick/client/index.html
tablet_tilt_joystick/client/script.js
tablet_tilt_joystick/client/style.css
tablet_tilt_joystick-1.2.1.dist-info/LICENSE
tablet_tilt_joystick-1.2.1.dist-info/METADATA
tablet_tilt_joystick-1.2.1.dist-info/WHEEL
tablet_tilt_joystick-1.2.1.dist-info/entry_points.txt
tablet_tilt_joystick-1.2.1.dist-info/top_level.txt
tablet_tilt_joystick-1.2.1.dist-info/RECORD
