Metadata-Version: 2.1
Name: tablet-tilt-joystick
Version: 1.2.1
Summary: Emulate a joystick by tilting your tablet.
Home-page: https://github.com/ThatCoolCoder/tablet-tilt-joystick
Author: ThatCoolCoder
License: UNKNOWN
Project-URL: Bug Tracker, https://github.com/ThatCoolCoder/tablet-tilt-joystick/issues
Platform: UNKNOWN
Classifier: Programming Language :: Python :: 3
Classifier: License :: OSI Approved :: MIT License
Classifier: Operating System :: POSIX
Requires-Python: >=3.7
License-File: LICENSE
Requires-Dist: eventlet
Requires-Dist: python-socketio
Requires-Dist: pillow
Requires-Dist: qrcode[pil]
Requires-Dist: python-uinput
